ayx_python_sdk/__init__.py
ayx_python_sdk/__main__.py
ayx_python_sdk/version.py
ayx_python_sdk/assets/base_tool_config/Config.xml
ayx_python_sdk/assets/base_tool_config/icon.png
ayx_python_sdk/assets/executables/yxi-installer.pyz
ayx_python_sdk/assets/workspace_files/__init__.py
ayx_python_sdk/assets/workspace_files/requirements-local.txt
ayx_python_sdk/assets/workspace_files/requirements-thirdparty.txt
ayx_python_sdk/assets/workspace_files/setup.py
ayx_python_sdk/cli/__init__.py
ayx_python_sdk/cli/utilities.py
ayx_python_sdk/cli/workspace.py
ayx_python_sdk/cli/yxi_builder.py
ayx_python_sdk/cli/yxi_installer.py
ayx_python_sdk/core/__init__.py
ayx_python_sdk/core/constants.py
ayx_python_sdk/core/dcm_base.py
ayx_python_sdk/core/doc_utilities.py
ayx_python_sdk/core/environment_base.py
ayx_python_sdk/core/exceptions.py
ayx_python_sdk/core/field.py
ayx_python_sdk/core/input_anchor_base.py
ayx_python_sdk/core/input_connection_base.py
ayx_python_sdk/core/io_base.py
ayx_python_sdk/core/metadata.py
ayx_python_sdk/core/observable_mixin.py
ayx_python_sdk/core/output_anchor_base.py
ayx_python_sdk/core/plugin.py
ayx_python_sdk/core/plugin_v2.py
ayx_python_sdk/core/provider_base.py
ayx_python_sdk/core/proxy_requests.py
ayx_python_sdk/core/record_packet.py
ayx_python_sdk/core/record_packet_base.py
ayx_python_sdk/core/register_plugin.py
ayx_python_sdk/core/testing.py
ayx_python_sdk/core/utils.py
ayx_python_sdk/docs/ayx_python_sdk.cli.html
ayx_python_sdk/docs/ayx_python_sdk.core.html
ayx_python_sdk/docs/ayx_python_sdk.html
ayx_python_sdk/docs/ayx_python_sdk.providers.amp_provider.builders.html
ayx_python_sdk/docs/ayx_python_sdk.providers.amp_provider.data_transport.html
ayx_python_sdk/docs/ayx_python_sdk.providers.amp_provider.grpc_helpers.html
ayx_python_sdk/docs/ayx_python_sdk.providers.amp_provider.html
ayx_python_sdk/docs/ayx_python_sdk.providers.amp_provider.repositories.html
ayx_python_sdk/docs/ayx_python_sdk.providers.amp_provider.resources.generated.html
ayx_python_sdk-2.5.1.dist-info/METADATA
ayx_python_sdk-2.5.1.dist-info/WHEEL
ayx_python_sdk-2.5.1.dist-info/entry_points.txt
ayx_python_sdk-2.5.1.dist-info/top_level.txt
ayx_python_sdk-2.5.1.dist-info/RECORD
