Metadata-Version: 2.4
Name: ayx_python_sdk
Version: 2.5.1
Summary: The Python plugin SDK for Alteryx Designer.
Author: Alteryx, Inc.
Author-email: support@alteryx.com
Platform: Windows
Classifier: Development Status :: 5 - Production/Stable
Classifier: Intended Audience :: Developers
Classifier: License :: Other/Proprietary License
Classifier: Operating System :: Microsoft :: Windows
Classifier: Programming Language :: Python :: 3.8
Classifier: Programming Language :: Python :: 3.10
Classifier: Topic :: Scientific/Engineering :: Information Analysis
Requires-Python: >=3.8, !=3.9.*, !=3.11.*, !=3.12.*, <3.14
Requires-Dist: Click==8.1.7
Requires-Dist: deprecation==2.1.0
Requires-Dist: grpcio-fips==1.70.0; sys_platform == "win32"
Requires-Dist: grpcio==1.70.0; sys_platform == "linux"
Requires-Dist: numpy<3.0,>=2.1.0
Requires-Dist: pandas<3.0,>=2.3.0
Requires-Dist: protobuf==5.29.5
Requires-Dist: psutil==7.0.0
Requires-Dist: pydantic==2.10.6
Requires-Dist: pyarrow==18.1.0
Requires-Dist: PyPAC==0.16.5
Requires-Dist: python-dateutil==2.8.2
Requires-Dist: pytz==2023.3.post1
Requires-Dist: requests>=2.32.4
Requires-Dist: six==1.16.0
Requires-Dist: typer==0.9.0
Requires-Dist: xmltodict==0.12.0
Requires-Dist: urllib3>=2.5.0
Requires-Dist: wincertstore==0.2
Dynamic: author
Dynamic: author-email
Dynamic: classifier
Dynamic: description
Dynamic: description-content-type
Dynamic: platform
Dynamic: requires-dist
Dynamic: requires-python
Dynamic: summary
